LICENCE.txt
MANIFEST.in
README.rst
setup.cfg
setup.py
django_smart_media.egg-info/PKG-INFO
django_smart_media.egg-info/SOURCES.txt
django_smart_media.egg-info/dependency_links.txt
django_smart_media.egg-info/requires.txt
django_smart_media.egg-info/top_level.txt
django_smart_media.egg-info/zip-safe
smart_media/__init__.py
smart_media/admin.py
smart_media/apps.py
smart_media/exceptions.py
smart_media/fields.py
smart_media/mixins.py
smart_media/modelfields.py
smart_media/settings.py
smart_media/signals.py
smart_media/thumbnailing.py
smart_media/validators.py
smart_media/widgets.py
smart_media/contrib/__init__.py
smart_media/contrib/django_configuration.py
smart_media/static/smart_image/css/fileinputbutton.css
smart_media/static/smart_image/js/fileinputbutton.js
smart_media/templates/smart_image/fileinputbutton_basic.html
smart_media/templates/smart_image/fileinputbutton_clearable.html
smart_media/templatetags/__init__.py
smart_media/templatetags/smart_image.py
smart_media/utils/__init__.py
smart_media/utils/factories.py
smart_media/utils/file.py
smart_media/utils/tests.py